[
  {
    "english_title": "Psalm 121 - I was glad for those...",
    "coptic_title": null,
    "arabic_title": "المزمورُ المائةُ والحادي والعشرونَ - فرِحتُ بالقائلينَ...",
    "title": "Psalm 121 - I was glad for those...",
    "tbodies": [
      {
        "rows": [
          {
            "row-class": "text",
            "cells": [
              {
                "english": "I was glad for those who said to me, “We will go into the house of the Lord.” Our feet stood in the courts of Jerusalem, Jerusalem which is built as a city that is closely compacted together. For there the tribes went up, the tribes of the Lord, as a testimony for Israel, to give thanks to the name of the Lord. For there are set thrones for judgment, even thrones for the house of David.",
                "arabic": "فرِحتُ بالقائلينَ لي إلى بيتِ الربِّ نذهبُ. وقفَت أرجُلُنا في ديارِ أورُشَليمَ، أورُشَليمُ المبنيَّةُ مِثلُ مدينةٍ مُتَّصِلةٍ بعضِها ببعضٍ. لأنَّ هُناكَ صعِدَتْ القبائلُ، قبائلُ الربِّ، شهادةً لإسرائيلَ، يعترِفونَ لاسمِ الربِّ. هُناكَ نُصِبَتْ كراسيُّ للقضاءِ، كراسيُّ بيتِ داودَ."
              }
            ]
          },
          {
            "row-class": "text",
            "cells": [
              {
                "english": "Ask for the things which are for the peace of Jerusalem, and for the prosperity to those who love you. Let peace be within your strength, and prosperity in your heavy towers. For the sake of my brethren and my companions, I have indeed spoken peace concerning you. Because of the house of the Lord our God, I have diligently sought good things for you. ALLELUIA.",
                "arabic": "اسألوا السلامَ لأورُشَليمَ والخِصبَ لمُحبّيكِ. ليكُنْ السلامُ في حِصنِكِ والخِصبُ في أبراجِكِ الرصينةِ. مِنْ أجلِ إخوتي وأقربائي تكلَّمتُ مِنْ أجلِكِ بالسلامِ، ومِنْ أجلِ بيتِ الربِّ إلهِنا التمستُ لكِ الخيراتِ. هَلِّلُويا."
              }
            ]
          }
        ]
      }
    ]
  },
  {
    "english_title": "Psalms 26:4-5",
    "coptic_title": null,
    "arabic_title": "مزامير 26: 4-5",
    "title": "Psalms 26:4-5",
    "tbodies": [
      {
        "rows": [
          {
            "row-class": "text",
            "cells": [
              {
                "english": "One thing I have asked of the Lord, this also I will seek, that I should dwell in the house of the Lord all the days of my life, that I should behold the fair beauty of the Lord, and visit His holy temple. For in the day of my afflictions He hid me in His tabernacle; He sheltered me in the secret of His tabernacle; He set me up on a rock.",
                "arabic": "واحدةً سألتُ مِنَ الربِّ وإيَّاها ألتمسُ. أن أسكنَ في بيتِ الربِّ كلَّ أيامِ حياتي. لكي أنظرَ نعيمَ الربِّ، وأتفرسَ في هيكلِهِ المُقدسِ. لأنَّه أخفاني في خيمتِهِ. في يومِ شِدَّتي، ستَرَني بسِترِ مظلَّتِهِ. وعلى صخرةٍ رفعَني."
              }
            ]
          }
        ]
      }
    ]
  },
  {
    "english_title": "Psalms 64:4",
    "coptic_title": null,
    "arabic_title": "مزامير 64: 4",
    "title": "Psalms 64:4",
    "tbodies": [
      {
        "rows": [
          {
            "row-class": "text",
            "cells": [
              {
                "english": "Blessed is the man You choose, And cause to approach You, That he may dwell in Your courts. We shall be satisfied with the goodness of Your house, Of Your holy temple.",
                "arabic": "طُوبَى لِلَّذِي تَخْتَارُهُ وَتُقَرِّبُهُ لِيَسْكُنَ فِي دِيَارِكَ. لَنَشْبَعَنَّ مِنْ خَيْرِ بَيْتِكَ قُدْسِ هَيْكَلِكَ."
              }
            ]
          }
        ]
      }
    ]
  },
  {
    "english_title": "Psalm 83 - How beloved are Your dwellings...",
    "coptic_title": null,
    "arabic_title": "المزمور الثالث والثمانون - مساكنُكَ محبوبةٌ...",
    "title": "Psalm 83 - How beloved are Your dwellings...",
    "tbodies": [
      {
        "rows": [
          {
            "row-class": "text",
            "cells": [
              {
                "english": "How beloved are Your dwellings, O Lord, God of hosts! My soul longs, and faints for the courts of the Lord; my heart and my flesh have exulted in the living God. For, the sparrow has found for himself a home, and the turtledove for herself a nest, where she may lay her young; Your altars, O Lord, God of hosts, my King, and my God.",
                "arabic": "مساكنُكَ محبوبةٌ ياربُّ إلهُ القواتِ. تشتاقُ وتذوبُ نفسي للدخولِ إلى ديارِ الربِّ. قلبي وجسمي قد ابتهجا بالإلهِ الحيِّ. لأنَّ العصفورَ وجدَ لهُ بيتاً، واليمامةَ عُشاً لتضعَ فيهِ أفراخَها. مذابحَكَ ياربُّ الهُ القواتِ، ملكي وإلهي."
              }
            ]
          },
          {
            "row-class": "text",
            "cells": [
              {
                "english": "Blessed are all who dwell in Your house; they will praise You forever and ever. Blessed is the man whose help is from You, O Lord; he sets paths upward in his heart in the valley of weeping, in the place which he has appointed, for there the Law-Giver will grant blessings. They shall go from strength to strength; the God of gods shall be revealed in Zion.",
                "arabic": "طوبى لكلِّ الساكنينَ في بيتِكَ، يباركونَكَ إلى الأبدِ. طوبى للرجلِ الذي نُصرتُهُ مِنْ عِندِكَ ياربُّ، رتِّبْ مصاعِدَ في قلبِهِ. في وادي البُكاءِ، في المكانِ الذي قرّرَهُ. لأنَّ البركاتِ يُعطيها واضعُ الناموسِ. يسيرونَ مِنْ قوةٍ إلى قوةٍ، يتجلّى إلهُ الآلهةِ في صِهيَونَ."
              }
            ]
          },
          {
            "row-class": "text",
            "cells": [
              {
                "english": "O Lord, God of hosts, hear my prayer; hearken, O God of Jacob. Behold, O God our defender, and look upon the face of Your anointed. For one day in Your courts is better than thousands. I chose to throw myself down in the house of God, more than to dwell in the tents of the sinners. For the Lord God loves mercy and truth; He shall give grace and glory; the Lord shall not withhold good things from those who walk in innocence. O Lord God of hosts, blessed is the man who hopes in You. ALLELUIA.",
                "arabic": "أيها الربُّ إلهُ القواتِ استمِعْ لصلاتي، أنصِتْ يا إلهَ يعقوبَ. وانظرْ أيها الإلهُ ناصِرُنا، واطّلِعْ إلى وجهِ مسيحِكَ. لأنَّ يوماً صالحاً في ديارِكَ خيرٌ مِنْ آلافٍ. اخترتُ لنفسي أن أُطرَحَ على بابِ بيتِ اللهِ، أفضلَ مِنْ أن أسكنَ في مظالِّ الخطاةِ. لأنَّ الربَّ الإلهَ يُحبُّ الرحمةَ والحقَّ، ويُعطي مجداً ونِعمةً. الربُّ لا يمنعُ الخيراتِ عن السالكينَ بالدعةِ. ياربُّ إلهُ القواتِ، طوبى للإنسانِ المتكلِ عليكَ. هَلِّلُويا."
              }
            ]
          }
        ]
      }
    ]
  },
  {
    "english_title": "Psalms 5:7",
    "coptic_title": null,
    "arabic_title": "مزامير 5: 7",
    "title": "Psalms 5:7",
    "tbodies": [
      {
        "rows": [
          {
            "row-class": "text",
            "cells": [
              {
                "english": "But as for me, according to the multitude of Your mercy I shall enter Your house; I shall worship before Your holy temple in Your fear.",
                "arabic": "أمَّا أنا فبكثرةِ رحمتِكَ أدخلُ بيتَكَ، وأسجدُ قدَّامَ هيكلِ قدسِكَ بمخافتِكَ."
              }
            ]
          }
        ]
      }
    ]
  },
  {
    "english_title": "Agpeya - Deacons.fixed",
    "coptic_title": null,
    "arabic_title": null,
    "title": "Agpeya - Deacons.fixed",
    "seasons": [
      "NativityPeriod",
      "NativityParamoun",
      "Circumcision"
    ],
    "tbodies": [
      {
        "rows": [
          {
            "row-class": "text",
            "cells": [
              {
                "english": "We worship You, O Christ, with Your good Father, and the Holy Spirit, for You were born and saved us. Have mercy on us.",
                "coptic": "Ⲧⲉⲛⲟⲩⲱϣⲧ ⲙ̀ⲙⲟⲕ ⲱ̀ Ⲡⲓⲭ̀ⲣⲓⲥⲧⲟⲥ: ⲛⲉⲙ Ⲡⲉⲕⲓⲱⲧ ⲛ̀ⲁ̀ⲅⲁⲑⲟⲥ: ⲛⲉⲙ Ⲡⲓⲡ̀ⲛⲉⲩⲙⲁ ⲉⲑⲟⲩⲁⲃ: ϫⲉ ⲁⲩⲙⲁⲥⲕ ⲁⲕⲥⲱϯ ⲙ̀ⲙⲟⲛ ⲛⲁⲓ ⲛⲁⲛ.",
                "arabic": "نسجدُ لكَ أيها المسيحُ، معَ أبيكَ الصالحِ والرّوحِ القُدُسِ، لأنكَ وُلِدتَ وخلَّصتَنا. [ارحَمْنا]"
              }
            ]
          }
        ]
      }
    ]
  },
  {
    "english_title": "Agpeya - Deacons.fixed",
    "coptic_title": null,
    "arabic_title": null,
    "title": "Agpeya - Deacons.fixed",
    "seasons": [
      "TheophanyPeriod",
      "TheophanyParamoun"
    ],
    "tbodies": [
      {
        "rows": [
          {
            "row-class": "text",
            "cells": [
              {
                "english": "We worship You, O Christ, with Your good Father, and the Holy Spirit, for You were baptized and saved us. Have mercy on us.",
                "coptic": "Ⲧⲉⲛⲟⲩⲱϣⲧ ⲙ̀ⲙⲟⲕ ⲱ̀ Ⲡⲓⲭ̀ⲣⲓⲥⲧⲟⲥ: ⲛⲉⲙ Ⲡⲉⲕⲓⲱⲧ ⲛ̀ⲁ̀ⲅⲁⲑⲟⲥ: ⲛⲉⲙ Ⲡⲓⲡ̀ⲛⲉⲩⲙⲁ ⲉⲑⲟⲩⲁⲃ: ϫⲉ ⲁⲕϭⲓⲱⲙⲥ ⲁⲕⲥⲱϯ ⲙ̀ⲙⲟⲛ ⲛⲁⲓ ⲛⲁⲛ.",
                "arabic": "نسجدُ لكَ أيها المسيحُ، معَ أبيكَ الصالحِ والرّوحِ القُدُسِ، لأنكَ أعتمدت وخلَّصتَنا. [ارحَمْنا]"
              }
            ]
          }
        ]
      }
    ]
  },
  {
    "english_title": "Agpeya - Deacons.fixed",
    "coptic_title": null,
    "arabic_title": null,
    "title": "Agpeya - Deacons.fixed",
    "seasons": [
      "PaschaWeek",
      "Pascha",
      "FeastOfTheCross",
      "(FuneralTune ^ FuneralPrayer)",
      "GeneralFuneralPrayer"
    ],
    "tbodies": [
      {
        "rows": [
          {
            "row-class": "text",
            "cells": [
              {
                "english": "We worship You, O Christ, with Your good Father, and the Holy Spirit, for You were crucified and saved us. Have mercy on us.",
                "coptic": "Ⲧⲉⲛⲟⲩⲱϣⲧ ⲙ̀ⲙⲟⲕ ⲱ̀ Ⲡⲓⲭ̀ⲣⲓⲥⲧⲟⲥ: ⲛⲉⲙ Ⲡⲉⲕⲓⲱⲧ ⲛ̀ⲁ̀ⲅⲁⲑⲟⲥ: ⲛⲉⲙ Ⲡⲓⲡ̀ⲛⲉⲩⲙⲁ ⲉⲑⲟⲩⲁⲃ: ϫⲉ ⲁⲩⲁϣⲕ ⲁⲕⲥⲱϯ ⲙ̀ⲙⲟⲛ ⲛⲁⲓ ⲛⲁⲛ.",
                "arabic": "نسجدُ لكَ أيها المسيحُ، معَ أبيكَ الصالحِ والرّوحِ القُدُسِ، لأنكَ صلبت وخلَّصتَنا. [ارحَمْنا]"
              }
            ]
          }
        ]
      }
    ]
  },
  {
    "english_title": "Agpeya - Deacons.fixed",
    "coptic_title": null,
    "arabic_title": null,
    "title": "Agpeya - Deacons.fixed",
    "seasons": [
      "!ThirdProstration ^ (Joyful29thOfTheMonthRaw",
      "PentecostPeriod",
      "(Sundays ^ ApostlesFastToLastDayOfHathor))"
    ],
    "tbodies": [
      {
        "rows": [
          {
            "row-class": "text",
            "cells": [
              {
                "english": "We worship You, O Christ, with Your good Father, and the Holy Spirit, for You have risen and saved us. Have mercy on us.",
                "coptic": "Ⲧⲉⲛⲟⲩⲱϣⲧ ⲙ̀ⲙⲟⲕ ⲱ̀ Ⲡⲓⲭ̀ⲣⲓⲥⲧⲟⲥ: ⲛⲉⲙ Ⲡⲉⲕⲓⲱⲧ ⲛ̀ⲁ̀ⲅⲁⲑⲟⲥ: ⲛⲉⲙ Ⲡⲓⲡ̀ⲛⲉⲩⲙⲁ ⲉⲑⲟⲩⲁⲃ: ϫⲉ ⲁⲕⲧⲱⲛⲕ ⲁⲕⲥⲱϯ ⲙ̀ⲙⲟⲛ ⲛⲁⲓ ⲛⲁⲛ.",
                "arabic": "نسجدُ لكَ أيها المسيحُ، معَ أبيكَ الصالحِ والرّوحِ القُدُسِ، لأنكَ قمت وخلَّصتَنا. [ارحَمْنا]"
              }
            ]
          }
        ]
      }
    ]
  },
  {
    "english_title": "Agpeya - Deacons.fixed",
    "coptic_title": null,
    "arabic_title": null,
    "title": "Agpeya - Deacons.fixed",
    "seasons": [
      "Other"
    ],
    "tbodies": [
      {
        "rows": [
          {
            "row-class": "text",
            "cells": [
              {
                "english": "We worship You, O Christ, with Your good Father, and the Holy Spirit, for You have come and saved us. Have mercy on us.",
                "coptic": "Ⲧⲉⲛⲟⲩⲱϣⲧ ⲙ̀ⲙⲟⲕ ⲱ̀ Ⲡⲓⲭ̀ⲣⲓⲥⲧⲟⲥ: ⲛⲉⲙ Ⲡⲉⲕⲓⲱⲧ ⲛ̀ⲁ̀ⲅⲁⲑⲟⲥ: ⲛⲉⲙ Ⲡⲓⲡ̀ⲛⲉⲩⲙⲁ ⲉⲑⲟⲩⲁⲃ: ϫⲉ ⲁⲕⲓ̀ ⲁⲕⲥⲱϯ ⲙ̀ⲙⲟⲛ ⲛⲁⲓ ⲛⲁⲛ.",
                "arabic": "نسجدُ لكَ أيها المسيحُ، معَ أبيكَ الصالحِ والرّوحِ القُدُسِ، لأنَّكَ أتيتَ وخلَّصتَنا. [ارحَمْنا]"
              }
            ]
          }
        ]
      }
    ]
  },
  {
    "english_title": "Psalm 122 - Unto You I have lifted...",
    "coptic_title": null,
    "arabic_title": "المزمورُ المائةُ والثاني والعشرونَ - إليكَ رفعتُ عينيَّ...",
    "title": "Psalm 122 - Unto You I have lifted...",
    "tbodies": [
      {
        "rows": [
          {
            "row-class": "text",
            "cells": [
              {
                "english": "Unto You I have lifted up my eyes, O You who dwell in heaven. Behold as the eyes of servants are unto to the hands of their masters, and as the eyes of a maidservant to the hands of her mistress; so our eyes are toward the Lord our God until He has pity on us. Have mercy on us, O Lord, have mercy on us, for we are exceedingly filled with contempt, and our soul has been exceedingly filled. Give the reproach to those who prosper, and contempt to the proud. ALLELUIA.",
                "arabic": "إليكَ رفعتُ عينيَّ يا ساكِنَ السماءِ. فها هُما مِثلُ عيونِ العبيدِ إلى أيدي مواليهِم، ومِثلُ عينيِّ الأمَةِ إلى يديِّ سيِّدتِها. كذلِكَ أعيُنُنا نحوَ الربِّ إلهِنا حتى يترأفَ علَينا. ارحمْنا ياربُّ ارحمْنا، فإنَّنا كثيراً ما امتلأنا هواناً، وكثيراً ما امتلأتْ نُفوسُنا، العارُ اردُدهُ على المُخصِبينَ والهوانُ على المُتعَّظمينَ. هَلِّلُويا."
              }
            ]
          }
        ]
      }
    ]
  },
  {
    "english_title": "Psalm 29 - I will exalt You...",
    "coptic_title": null,
    "arabic_title": "المزمور التاسع والعشرون - أعظمُكَ ياربُّ...",
    "title": "Psalm 29 - I will exalt You...",
    "tbodies": [
      {
        "rows": [
          {
            "row-class": "text",
            "cells": [
              {
                "english": "I will exalt You, O Lord, for You have accepted me, and not caused my enemies to rejoice over me. O Lord, my God, I cried to You, and You have healed me. O Lord, You have brought up my soul from Hades, You have delivered me from those who will go down to the pit.",
                "arabic": "أعظِّمُكَ ياربُّ لأنكَ احتضنتَني، ولم تُشمِتْ بي أعدائي. أيُها الربُّ إلهي، صرختُ إليكَ فشفَيتَني. ياربُّ أصعدتَ مِنَ الجحيمِ نفسي، وخلّصتَني مِنَ الهابطينَ في الجُبِّ."
              }
            ]
          },
          {
            "row-class": "text",
            "cells": [
              {
                "english": "Sing to the Lord, all you His saints, and confess the remembrance of His holiness. For anger is in His wrath, but life in His favor; weeping shall be for the evening, but joy shall be in the morning.",
                "arabic": "رتّلوا للربِّ يا جميعَ قديسيهِ، واعترفوا لذكرِ قُدسِهِ. لأنَّ سَخَطاً في غضبِهِ، وحياةً في رضاهُ. في العشاءِ يحلُّ البكاءُ، وفي الصباحِ السرورُ."
              }
            ]
          },
          {
            "row-class": "text",
            "cells": [
              {
                "english": "I said in my prosperity, I shall never be moved. O Lord, in Your will You gave strength to my beauty, but You turned away Your face from me, and I became troubled. To You, O Lord, I shall cry, and to my God I shall make supplication. What profit is there in my blood, when I go down to destruction? Shall the dust confess to You? Or shall it declare Your truth?",
                "arabic": "أنا قلتُ في نعيمي لا أتزعزعُ إلى الدهرِ، ياربُّ بمسرَّتِكَ أعطيتَ جَمالي قوةً. صرفتَ وجهَكَ عنّي، فصِرتُ قلِقاً. إليكَ ياربُّ أصرخُ، وإلى إلهي أتضرَّعُ. أيّةُ منفعةٍ مِنْ دمي إذا هبَطتُ إلى الجحيمِ؟ هل يعترفُ لكَ الترابُ أو يُخبرُ بحقِّكَ؟"
              }
            ]
          },
          {
            "row-class": "text",
            "cells": [
              {
                "english": "The Lord heard, and had mercy upon me; the Lord became to me a helper. You have turned my mourning into joy for me; You have rent off my sackcloth, and girded me with gladness, that my glory may sing praise to You, and I shall not be troubled at heart. O Lord, my God, I will confess to You forever. ALLELUIA.",
                "arabic": "سمعَ الربُّ فرحمَني، الربُّ صارَ لي عوناً. حوّلتَ نَوحي إلى فرحٍ لي، مزّقتَ مِسْحي ومنطقتَني سُروراً. لكي تُرتِلَ لكَ نفسي ولا يحزنَ قلبي. أيُها الربُّ إلهي إلى الأبدِ أعترفُ لكَ. هَلِّلُويا."
              }
            ]
          }
        ]
      }
    ]
  },
  {
    "english_title": "Psalm 92 - The Lord has reigned; He has clothed...",
    "coptic_title": null,
    "arabic_title": "المزمور الثاني والتسعون - الربُّ قد ملكَ، ولبسَ...",
    "title": "Psalm 92 - The Lord has reigned; He has clothed...",
    "tbodies": [
      {
        "rows": [
          {
            "row-class": "text",
            "cells": [
              {
                "english": "The Lord has reigned; He has clothed Himself with beauty. The Lord has clothed and girded Himself with strength; for He has established the world, which shall not be moved. Your throne is prepared from the beginning; You are from everlasting. The rivers have lifted up, O Lord; the rivers have lifted up their voices; the rivers shall lift up their voices, from the voices of many waters. The billows of the waves of the sea are wonderful; the Lord is wonderful in the highest. His testimonies are very sure; holiness is worthy of Your house, O Lord, unto length of days. ALLELUIA.",
                "arabic": "الربُّ قد ملَكَ، ولبِسَ الجلالَ. لبِسَ الربُّ القوةَ، وتمنطقَ بها. لأنَّهُ ثبَّتَ المسكونةَ فلن تتزعزعَ. كرسيُّكَ ثابتٌ مُنذُ البدءِ، وأنتَ هو مُنذُ الأزلِ. رفعتِ الأنهارُ ياربُّ، رفعتِ الأنهارُ صوتَها. ترفعُ الأنهارُ صوتَها، مِنْ صوتِ مياهٍ كثيرةٍ. عجيبةٌ هي أهوالُ البحرِ، وعجيبٌ هو الربُّ في الأعالي. شهاداتُهُ صادقةٌ جداً، لبيتِكَ ينبغي التقديسُ ياربُّ طولَ الأيامِ. هَلِّلُويا."
              }
            ]
          }
        ]
      }
    ]
  }
]
